terrakio_admin_api/__init__.py
terrakio_admin_api-0.5.23.dist-info/METADATA
terrakio_admin_api-0.5.23.dist-info/WHEEL
terrakio_admin_api-0.5.23.dist-info/RECORD
