Metadata-Version: 2.4
Name: terrakio-admin-api
Version: 0.5.23
Summary: Admin version of the terrakio-python-api
Requires-Python: >=3.11
Requires-Dist: terrakio-core==0.5.23
